zerocut/__init__.py
zerocut/core.py
zerocut/frame.py
zerocut/frames/sample.py
zerocut/frames/samples/black.png
zerocut/frames/samples/white.png
zerocut-0.1.9.dist-info/METADATA
zerocut-0.1.9.dist-info/WHEEL
zerocut-0.1.9.dist-info/RECORD
