Metadata-Version: 2.3
Name: zerocut
Version: 0.1.9
Summary: 
Author: ZeroOneDeveloper
Author-email: me@zero0ne.dev
Requires-Python: >=3.13
Classifier: Programming Language :: Python :: 3
Classifier: Programming Language :: Python :: 3.13
Requires-Dist: pillow (>=11.2.1,<12.0.0)
